inhandtest/__init__.py
inhandtest/er_events.yaml
inhandtest/exception.py
inhandtest/file.py
inhandtest/inexpect.py
inhandtest/inmodbus.py
inhandtest/inmongodb.py
inhandtest/inmqtt.py
inhandtest/inserial.py
inhandtest/insocket.py
inhandtest/inssh.py
inhandtest/ip.py
inhandtest/log.py
inhandtest/mail.py
inhandtest/notice_email.html
inhandtest/pytest_email.html
inhandtest/telnet.py
inhandtest/telnet.yaml
inhandtest/tools.py
inhandtest/base_page/__init__.py
inhandtest/base_page/_contents_locators.py
inhandtest/base_page/_ir3XX_contents_locators.py
inhandtest/base_page/_vg710_contents_locators.py
inhandtest/base_page/base_page.py
inhandtest/base_page/contents_locale.yaml
inhandtest/base_page/login_config.yaml
inhandtest/base_page/page.py
inhandtest/base_page/table_tr.py
inhandtest/inrequest/__init__.py
inhandtest/inrequest/console.py
inhandtest/inrequest/dm.py
inhandtest/inrequest/dn.py
inhandtest/inrequest/er_default_config.py
inhandtest/inrequest/er_device.py
inhandtest/inrequest/ics.py
inhandtest/inrequest/inrequest.py
inhandtest/inrequest/link.py
inhandtest/inrequest/nezha.py
inhandtest/inrequest/oms.py
inhandtest/openvpn_tools_in_windows/__init__.py
inhandtest/openvpn_tools_in_windows/openvpn_tools.py
inhandtest/pages/__init__.py
inhandtest/pages/adapt_model_locator.py
inhandtest/pages/er_device/__init__.py
inhandtest/pages/er_device/eap600/__init__.py
inhandtest/pages/er_device/eap600/config.py
inhandtest/pages/er_device/eap600/eap600.py
inhandtest/pages/er_device/er2000/__init__.py
inhandtest/pages/er_device/er2000/er2000.py
inhandtest/pages/er_device/er2000/local_network.py
inhandtest/pages/er_device/er2000/security.py
inhandtest/pages/er_device/er2000/services.py
inhandtest/pages/er_device/er2000/status.py
inhandtest/pages/er_device/er2000/system.py
inhandtest/pages/er_device/er2000/vpn.py
inhandtest/pages/er_device/er805/__init__.py
inhandtest/pages/er_device/er805/er805.py
inhandtest/pages/er_device/er805/local_network.py
inhandtest-0.0.81.dist-info/METADATA
inhandtest-0.0.81.dist-info/WHEEL
inhandtest-0.0.81.dist-info/top_level.txt
inhandtest-0.0.81.dist-info/RECORD
