Metadata-Version: 2.1
Name: inhandtest
Version: 0.0.81
Summary: inhand test tools, so easy
Home-page: https://inhandnetworks.yuque.com/irhb08/mrpu1r/qgu0imvigkm2xry9?singleDoc# 《inhandtest docs》
Author: liwei
Author-email: liwei@inhand.com.cn
Maintainer: liwei
Maintainer-email: liwei@inhand.com.cn
Classifier: Programming Language :: Python :: 3.7
Requires-Dist: pytz
Requires-Dist: requests
Requires-Dist: playwright ==1.40.0
Requires-Dist: pyserial
Requires-Dist: modbus-tk
Requires-Dist: paho-mqtt
Requires-Dist: urllib3
Requires-Dist: paramiko
Requires-Dist: emails
Requires-Dist: flash
Requires-Dist: Jinja2 ==3.1.2
Requires-Dist: pymongo
Requires-Dist: psutil
Requires-Dist: lxml
Requires-Dist: dynaconf
Requires-Dist: colorlog
Requires-Dist: pandas
Requires-Dist: pyyaml
Requires-Dist: speedtest-cli
Requires-Dist: python-consul
Requires-Dist: allure-pytest
Requires-Dist: telnetlib3
